[
  {
    "code": "018043",
    "name": "天弘纳斯达克100指数(QDII)A",
    "planType": "daily",
    "baseAmount": 40,
    "enabled": true
  },
  {
    "code": "006479",
    "name": "广发纳斯达克100ETF联接(QDII)C",
    "planType": "daily",
    "baseAmount": 10,
    "enabled": true
  },
  {
    "code": "008763",
    "name": "天弘越南市场股票(QDII)A",
    "planType": "weekly",
    "baseAmount": 40,
    "enabled": true
  },
  {
    "code": "270042",
    "name": "广发纳斯达克100ETF联接(QDII)A",
    "planType": "daily",
    "baseAmount": 50,
    "enabled": true
  },
  {
    "code": "016452",
    "name": "南方纳斯达克100指数(QDII)A",
    "planType": "weekly",
    "baseAmount": 50,
    "enabled": true
  },
  {
    "code": "017730",
    "name": "嘉实全球产业升级股票(QDII)A",
    "planType": "daily",
    "baseAmount": 28,
    "enabled": true
  },
  {
    "code": "016664",
    "name": "天弘全球高端制造混合(QDII)A",
    "planType": "daily",
    "baseAmount": 28,
    "enabled": true
  },
  {
    "code": "012920",
    "name": "易方达全球成长精选混合(QDII)A",
    "planType": "daily",
    "baseAmount": 28,
    "enabled": true
  }
]
